LICENSE.txt
README.md
setup.cfg
setup.py
tests/test_bundle.py
tests/test_client.py
tests/test_file.py
tests/test_organization.py
tests/test_project.py
warehouse/__init__.py
warehouse/__main__.py
warehouse/bundle.py
warehouse/client.py
warehouse/errors.py
warehouse/file.py
warehouse/organization.py
warehouse/project.py
warehouse/sorting.py
warehouse_client.egg-info/PKG-INFO
warehouse_client.egg-info/SOURCES.txt
warehouse_client.egg-info/dependency_links.txt
warehouse_client.egg-info/requires.txt
warehouse_client.egg-info/top_level.txt