Metadata-Version: 2.4
Name: warehouse-client
Version: 1.0.11
Summary: Client library to interact with levinsen software warehouse artifact management system.
Home-page: https://github.com/levinsen-software/warehouse-python
Author: levinsen software
Author-email: opensource@levinsen.software
License: MIT
Classifier: Development Status :: 5 - Production/Stable
Classifier: Intended Audience :: Developers
Classifier: Topic :: Software Development :: Build Tools
Classifier: License :: OSI Approved :: MIT License
Classifier: Programming Language :: Python :: 3
License-File: LICENSE.txt
Requires-Dist: requests
Dynamic: author
Dynamic: author-email
Dynamic: classifier
Dynamic: description
Dynamic: description-content-type
Dynamic: home-page
Dynamic: license
Dynamic: license-file
Dynamic: requires-dist
Dynamic: summary
